{"name":"SquareShells","tagline":"Designs and builds software","body":"### Welcome SquareShells.\r\nSquareShells was founded by @barksten in 2014. \r\n\r\nSquareShells are focused on (but not limited to) iOS and Mac software. We're always interested in collaboration projects!\r\n\r\n### Support or Contact\r\nHaving some trouble with this or just some questions? Email contact@squareshells.com and you'll be heard. If you prefer a shorter message you can tweet to [@squareshells](http://twitter.com/squareshells).","google":"UA-52149773-1","note":"Don't delete this file! It's used internally to help with page regeneration."}